Metadata-Version: 2.1
Name: random-attempt-1
Version: 0.0.1
Summary: SMARTS zoo agent.
Home-page: https://github.com/huawei-noah/SMARTS
Classifier: Programming Language :: Python
Classifier: Programming Language :: Python :: 3 :: Only
Classifier: Programming Language :: Python :: 3.8
Requires-Python: ==3.8.*
